LICENSE.md
MANIFEST.in
README.rst
setup.py
dagpy/__init__.py
dagpy/__main__.py
dagpy/api.py
dagpy/blockio.py
dagpy/dag.py
dagpy/dagexecutor.py
dagpy/flowmanager.py
dagpy/header_cell.txt
dagpy/utils.py
dagpy.egg-info/PKG-INFO
dagpy.egg-info/SOURCES.txt
dagpy.egg-info/dependency_links.txt
dagpy.egg-info/entry_points.txt
dagpy.egg-info/not-zip-safe
dagpy.egg-info/requires.txt
dagpy.egg-info/top_level.txt