Metadata-Version: 1.1
Name: dagpy
Version: 0.3.2
Summary: Data science collaboration tool based on iPython notebooks.
Home-page: https://github.com/ibestvina/dagpy
Author: Ivan Bestvina
Author-email: ivan.bestvina@gmail.com
License: MIT
Keywords: jupyter ipython collaboration dag datasci
Platform: UNKNOWN
Classifier: Development Status :: 3 - Alpha
Classifier: License :: OSI Approved :: MIT License
Classifier: Programming Language :: Python :: 3.4
